.testr.conf
AUTHORS
CONTRIBUTING.rst
ChangeLog
HACKING.rst
LICENSE
MANIFEST.in
README.rst
build_pdf.sh
openstack-common.conf
requirements.txt
setup.cfg
setup.py
test-requirements.txt
tox.ini
debian/changelog
debian/compat
debian/control
debian/copyright
debian/pyversions
debian/rules
doc/command.rst
doc/conf.py
doc/examples.rst
doc/index.rst
doc/installation.rst
doc/introduction.rst
libraclient/__init__.py
libraclient/client.py
libraclient/shell.py
libraclient/utils.py
libraclient/openstack/__init__.py
libraclient/openstack/common/__init__.py
libraclient/openstack/common/cliutils.py
libraclient/openstack/common/gettextutils.py
libraclient/openstack/common/importutils.py
libraclient/openstack/common/strutils.py
libraclient/openstack/common/apiclient/__init__.py
libraclient/openstack/common/apiclient/auth.py
libraclient/openstack/common/apiclient/base.py
libraclient/openstack/common/apiclient/client.py
libraclient/openstack/common/apiclient/exceptions.py
libraclient/openstack/common/apiclient/fake_client.py
libraclient/openstack/common/apiclient/keystone.py
libraclient/openstack/common/py3kcompat/__init__.py
libraclient/openstack/common/py3kcompat/urlutils.py
libraclient/v1_1/__init__.py
libraclient/v1_1/algorithms.py
libraclient/v1_1/base.py
libraclient/v1_1/client.py
libraclient/v1_1/limits.py
libraclient/v1_1/loadbalancer.py
libraclient/v1_1/protocols.py
libraclient/v1_1/shell.py
python_libraclient.egg-info/PKG-INFO
python_libraclient.egg-info/SOURCES.txt
python_libraclient.egg-info/dependency_links.txt
python_libraclient.egg-info/entry_points.txt
python_libraclient.egg-info/not-zip-safe
python_libraclient.egg-info/requires.txt
python_libraclient.egg-info/top_level.txt
tests/__init__.py