Metadata-Version: 1.1
Name: python-libraclient
Version: 2.0.0
Summary: Client library for Libra LBaaS tools
Home-page: https://launchpad.net/libra
Author: Andrew Hutchings
Author-email: andrew@linuxjedi.co.uk
License: Apache License, Version 2.0
Platform: UNKNOWN
Classifier: Development Status :: 5 - Production/Stable
Classifier: Environment :: Console
Classifier: Environment :: OpenStack
Classifier: Intended Audience :: Developers
Classifier: Intended Audience :: Information Technology
Classifier: License :: OSI Approved :: Apache Software License
Classifier: Operating System :: OS Independent
Classifier: Programming Language :: Python
